pyusername/__init__.py
pyusername/generate_username.py
pyusername-0.1.dist-info/LICENSE.txt
pyusername-0.1.dist-info/METADATA
pyusername-0.1.dist-info/WHEEL
pyusername-0.1.dist-info/top_level.txt
pyusername-0.1.dist-info/RECORD
