Metadata-Version: 2.1
Name: pyusername
Version: 0.1
Summary: A package for generating usernames based on names
Home-page: https://github.com/axelrothing/py-username/tree/main
Author: Axel Rothing
Author-email: axelrothing@icloud.com
Classifier: Programming Language :: Python :: 3
Classifier: License :: OSI Approved :: MIT License
Classifier: Operating System :: OS Independent
Requires-Python: >=3.6
License-File: LICENSE.txt
